allure/__init__.py
allure/adaptor.py
allure/common.py
allure/constants.py
allure/pytest_plugin.py
allure/rules.py
allure/structure.py
allure/utils.py
pytest_allure_adaptor-1.7.9.dist-info/DESCRIPTION.rst
pytest_allure_adaptor-1.7.9.dist-info/METADATA
pytest_allure_adaptor-1.7.9.dist-info/RECORD
pytest_allure_adaptor-1.7.9.dist-info/WHEEL
pytest_allure_adaptor-1.7.9.dist-info/entry_points.txt
pytest_allure_adaptor-1.7.9.dist-info/metadata.json
pytest_allure_adaptor-1.7.9.dist-info/top_level.txt
