Metadata-Version: 2.0
Name: pytest-allure-adaptor
Version: 1.7.9
Summary: Plugin for py.test to generate allure xml reports
Home-page: https://github.com/allure-framework/allure-pytest
Author: pupssman
Author-email: pupssman@yandex-team.ru
License: UNKNOWN
Platform: UNKNOWN
Requires-Dist: enum34
Requires-Dist: lxml (>=3.2.0)
Requires-Dist: namedlist
Requires-Dist: pytest (>=2.7.3)
Requires-Dist: six (>=1.9.0)
